langchain_outline/__init__.py
langchain_outline/document_loaders/outline.py
langchain_outline-0.2.0.dist-info/METADATA
langchain_outline-0.2.0.dist-info/WHEEL
langchain_outline-0.2.0.dist-info/RECORD
