Metadata-Version: 2.3
Name: langchain-outline
Version: 0.2.0
Summary: Langchain Document loader for Outline
Author: Diego Tabares
Author-email: diego.tabares@10pines.com
Requires-Python: >=3.9,<3.13
Classifier: Programming Language :: Python :: 3
Classifier: Programming Language :: Python :: 3.9
Classifier: Programming Language :: Python :: 3.10
Classifier: Programming Language :: Python :: 3.11
Classifier: Programming Language :: Python :: 3.12
Requires-Dist: langchain-community (>=0.3.21,<0.4.0)
Requires-Dist: langchain-core (>=0.3.52,<0.4.0)
Project-URL: Homepage, https://github.com/10Pines/langchain-outline
